cython_functions.cpython-39-darwin.so
cycpd/expectation_maximization_registration.py
cycpd/deformable_registration.py
cycpd/__init__.py
cycpd/rigid_registration.py
cycpd/affine_registration.py
cycpd-0.28.dist-info/RECORD
cycpd-0.28.dist-info/LICENSE
cycpd-0.28.dist-info/WHEEL
cycpd-0.28.dist-info/top_level.txt
cycpd-0.28.dist-info/METADATA
