Metadata-Version: 2.1
Name: cycpd
Version: 0.28
Summary: Numpy + Cython Implementation of the Coherent Point Drift Algorithm
Home-page: https://github.com/gattia/cycpd
Author: Anthony Gatti
Author-email: anthony@neuralseg.com
License: MIT
Keywords: image processing,point cloud,registration,mesh,surface
Classifier: Development Status :: 3 - Alpha
Classifier: License :: OSI Approved :: MIT License
Classifier: Topic :: Scientific/Engineering
License-File: LICENSE
Requires-Dist: numpy
